README.rst
hidapi.py
setup.py
hidapi_cffi.egg-info/PKG-INFO
hidapi_cffi.egg-info/SOURCES.txt
hidapi_cffi.egg-info/dependency_links.txt
hidapi_cffi.egg-info/top_level.txt