Metadata-Version: 1.0
Name: hidapi-cffi
Version: 0.2.1
Summary: CFFI wrapper for hidapi
Home-page: http://github.com/jbaiter/hidapi-cffi.git
Author: Johannes Baiter
Author-email: johannes.baiter@gmail.com
License: BSD
Platform: UNKNOWN
